omgxbeyler/__init__.py
omgxbeyler/matematik/AsalMi.py
omgxbeyler/matematik/Fibonacci.py
omgxbeyler/matematik/Permutasyon.py
omgxbeyler/matematik/Pi.py
omgxbeyler/matematik/__init__.py
omgxbeyler/oynat/__init__.py
omgxbeyler/oynat/KendinOynat/__init__.py
omgxbeyler/oynat/KendinOynat/cal.py
omgxbeyler/oynat/kategori/__init__.py
omgxbeyler/oynat/kategori/hayvanlar/__init__.py
omgxbeyler/oynat/kategori/hayvanlar/sesler.py
omgxbeyler/oynat/kategori/milyoner/__init__.py
omgxbeyler/oynat/kategori/milyoner/sesler.py
omgxbeyler/oynat/kategori/omgOzel/__init__.py
omgxbeyler/oynat/kategori/omgOzel/sesler.py
omgxbeyler/sifreleme/__init__.py
omgxbeyler/sifreleme/sezar/__init__.py
omgxbeyler/sifreleme/sezar/coz.py
omgxbeyler-1.0.0.dist-info/LICENSE
omgxbeyler-1.0.0.dist-info/METADATA
omgxbeyler-1.0.0.dist-info/WHEEL
omgxbeyler-1.0.0.dist-info/top_level.txt
omgxbeyler-1.0.0.dist-info/RECORD
