Metadata-Version: 2.1
Name: omgxbeyler
Version: 1.0.0
Summary: Kolay kullanımlı OMG Python kütüphanesi, WAV dosyalarını oynatma ve örnekler içerir.
Home-page: https://github.com/kullanici/omg
Author: Recep
Author-email: mrecepdeniz5454@gmail.com
License: UNKNOWN
Platform: UNKNOWN
Classifier: Programming Language :: Python :: 3
Classifier: License :: OSI Approved :: MIT License
Classifier: Operating System :: OS Independent
Requires-Python: >=3.7
License-File: LICENSE
Requires-Dist: pygame>=2.0.0
Requires-Dist: requests>=2.0.0
